odoo/addons/mail_footer_notified_partner/README.rst
odoo/addons/mail_footer_notified_partner/__init__.py
odoo/addons/mail_footer_notified_partner/__manifest__.py
odoo/addons/mail_footer_notified_partner/i18n/am.po
odoo/addons/mail_footer_notified_partner/i18n/ar.po
odoo/addons/mail_footer_notified_partner/i18n/bg.po
odoo/addons/mail_footer_notified_partner/i18n/bs.po
odoo/addons/mail_footer_notified_partner/i18n/ca.po
odoo/addons/mail_footer_notified_partner/i18n/cs.po
odoo/addons/mail_footer_notified_partner/i18n/da.po
odoo/addons/mail_footer_notified_partner/i18n/de.po
odoo/addons/mail_footer_notified_partner/i18n/el_GR.po
odoo/addons/mail_footer_notified_partner/i18n/en_GB.po
odoo/addons/mail_footer_notified_partner/i18n/es.po
odoo/addons/mail_footer_notified_partner/i18n/es_CR.po
odoo/addons/mail_footer_notified_partner/i18n/es_EC.po
odoo/addons/mail_footer_notified_partner/i18n/es_MX.po
odoo/addons/mail_footer_notified_partner/i18n/es_VE.po
odoo/addons/mail_footer_notified_partner/i18n/et.po
odoo/addons/mail_footer_notified_partner/i18n/eu.po
odoo/addons/mail_footer_notified_partner/i18n/fi.po
odoo/addons/mail_footer_notified_partner/i18n/fr.po
odoo/addons/mail_footer_notified_partner/i18n/fr_CA.po
odoo/addons/mail_footer_notified_partner/i18n/fr_CH.po
odoo/addons/mail_footer_notified_partner/i18n/gl.po
odoo/addons/mail_footer_notified_partner/i18n/hr.po
odoo/addons/mail_footer_notified_partner/i18n/hr_HR.po
odoo/addons/mail_footer_notified_partner/i18n/hu.po
odoo/addons/mail_footer_notified_partner/i18n/it.po
odoo/addons/mail_footer_notified_partner/i18n/ja.po
odoo/addons/mail_footer_notified_partner/i18n/lt.po
odoo/addons/mail_footer_notified_partner/i18n/lv.po
odoo/addons/mail_footer_notified_partner/i18n/mail_footer_notified_partner.pot
odoo/addons/mail_footer_notified_partner/i18n/mk.po
odoo/addons/mail_footer_notified_partner/i18n/mn.po
odoo/addons/mail_footer_notified_partner/i18n/nb.po
odoo/addons/mail_footer_notified_partner/i18n/nb_NO.po
odoo12_addon_mail_footer_notified_partner-12.0.1.0.0.99.dev10.dist-info/METADATA
odoo12_addon_mail_footer_notified_partner-12.0.1.0.0.99.dev10.dist-info/WHEEL
odoo12_addon_mail_footer_notified_partner-12.0.1.0.0.99.dev10.dist-info/top_level.txt
odoo12_addon_mail_footer_notified_partner-12.0.1.0.0.99.dev10.dist-info/RECORD
